{
    "input_path": "pdf/중급_금융투자상품.pdf",
    "page_index": 15,
    "page_count": 19,
    "width": 1191,
    "height": 1684,
    "model_settings": {
        "use_doc_preprocessor": false,
        "use_layout_detection": true,
        "use_chart_recognition": false,
        "format_block_content": false,
        "merge_layout_blocks": true,
        "markdown_ignore_labels": [
            "number",
            "footnote",
            "header",
            "header_image",
            "footer",
            "footer_image",
            "aside_text"
        ]
    },
    "parsing_res_list": [
        {
            "block_label": "text",
            "block_content": "[별지 5] 투자권유 희망 및 투자자정보 제공 여부 확인서",
            "block_bbox": [
                65,
                74,
                592,
                104
            ],
            "block_id": 0,
            "block_order": 1,
            "group_id": 0
        },
        {
            "block_label": "text",
            "block_content": "동 확인서는 투자자가 투자성 상품을 가입하는 경우 투자권유 희망 및 투자자정보 제공 의사를 확인하기 위해 마련되었습니다.",
            "block_bbox": [
                64,
                128,
                1122,
                192
            ],
            "block_id": 1,
            "block_order": 2,
            "group_id": 1
        },
        {
            "block_label": "text",
            "block_content": "o 투자자는 아래의 유의사항을 반드시 읽고 필요한 확인 절차를 거쳐주시기 바랍니다.",
            "block_bbox": [
                66,
                200,
                786,
                229
            ],
            "block_id": 2,
            "block_order": 3,
            "group_id": 2
        },
        {
            "block_label": "text",
            "block_content": "ㅇ 동 확인서는 향후 분쟁 또는 소송이 발생하는 경우 귀하의 권리구제에 불리하게 사용될 수 있으므로 신중하게 작성할 필요가 있습니다.",
            "block_bbox": [
                65,
                236,
                1122,
                301
            ],
            "block_id": 3,
            "block_order": 4,
            "group_id": 3
        },
        {
            "block_label": "paragraph_title",
            "block_content": "유의사항",
            "block_bbox": [
                113,
                347,
                191,
                376
            ],
            "block_id": 4,
            "block_order": 5,
            "group_id": 4
        },
        {
            "block_label": "text",
            "block_content": "1. 귀하께서 투자권유를 희망하지 않거나 투자자 정보를 제공하지 않는 경우 은행은 후술하는 적합성 원칙 준수 의무를 부담하지 않습니다.",
            "block_bbox": [
                77,
                398,
                1061,
                463
            ],
            "block_id": 5,
            "block_order": 6,
            "group_id": 5
        },
        {
            "block_label": "text",
            "block_content": "* 적합성 원칙(금융소비자보호법 제17조): 소비자의 재산상황, 금융상품 취득·처분 경험 등 정보를 파악하고, 소비자에게 부적합한 금융상품의 계약 체결 권유를 금지",
            "block_bbox": [
                102,
                471,
                1010,
                536
            ],
            "block_id": 6,
            "block_order": 7,
            "group_id": 6
        },
        {
            "block_label": "text",
            "block_content": "2. 귀하께서 투자권유를 희망하지 않거나 설명을 요청하지 않는 경우 은행은 후술하는 설명의무를 부담하지 않습니다.",
            "block_bbox": [
                76,
                578,
                1049,
                608
            ],
            "block_id": 7,
            "block_order": 8,
            "group_id": 7
        },
        {
            "block_label": "text",
            "block_content": "* 설명의무(금융소비자보호법 제19조): 금융상품의 중요사항을 소비자가 이해할 수 있도록 설명",
            "block_bbox": [
                96,
                615,
                900,
                645
            ],
            "block_id": 8,
            "block_order": 9,
            "group_id": 8
        },
        {
            "block_label": "paragraph_title",
            "block_content": "투자자 확인사항",
            "block_bbox": [
                113,
                704,
                252,
                732
            ],
            "block_id": 9,
            "block_order": 10,
            "group_id": 9
        },
        {
            "block_label": "text",
            "block_content": "상기 기재한 유의사항에 대해 설명을 듣고 투자권유 여부를 결정하신 경우 아래 각 항목의 해당사항에 체크한 후 밑줄 친 곳에 똑같이 자필로 기재하고 서명 또는 기명날인하시기 바랍니다.",
            "block_bbox": [
                81,
                746,
                1086,
                811
            ],
            "block_id": 10,
            "block_order": 11,
            "group_id": 10
        },
        {
            "block_label": "text",
            "block_content": "1. 투자권유 희망 여부",
            "block_bbox": [
                88,
                842,
                280,
                869
            ],
            "block_id": 11,
            "block_order": 12,
            "group_id": 11
        },
        {
            "block_label": "text",
            "block_content": "□ (투자권유를 희망하지 않음)",
            "block_bbox": [
                125,
                887,
                402,
                918
            ],
            "block_id": 12,
            "block_order": 13,
            "group_id": 12
        },
        {
            "block_label": "text",
            "block_content": "2. 투자자정보 제공 여부",
            "block_bbox": [
                87,
                958,
                298,
                985
            ],
            "block_id": 13,
            "block_order": 14,
            "group_id": 13
        },
        {
            "block_label": "text",
            "block_content": "□ (투자자정보를 제공함 )",
            "block_bbox": [
                126,
                1048,
                359,
                1078
            ],
            "block_id": 14,
            "block_order": 15,
            "group_id": 14
        },
        {
            "block_label": "text",
            "block_content": "□ (투자자정보를 제공하지 않음)\n※ 적정성 원칙 대상 상품 거래 희망 시 체크불가",
            "block_bbox": [
                616,
                1031,
                1035,
                1098
            ],
            "block_id": 15,
            "block_order": 16,
            "group_id": 15
        },
        {
            "block_label": "text",
            "block_content": "·투자권유를 희망하지 않거나 투자자정보를 제공하지 않는 경우에는 고객의 별도의사가 있기 전까지 은행이 투자 권유를 할 수 없습니다.",
            "block_bbox": [
                94,
                1135,
                930,
                1200
            ],
            "block_id": 16,
            "block_order": 17,
            "group_id": 16
        },
        {
            "block_label": "text",
            "block_content": "·투자시 원금 손실이 발생할 수 있으며, 투자 손익에 대한 책임은 모두 고객에게 귀속됩니다.",
            "block_bbox": [
                94,
                1231,
                869,
                1260
            ],
            "block_id": 17,
            "block_order": 18,
            "group_id": 17
        }
    ],
    "layout_det_res": {
        "input_path": null,
        "page_index": null,
        "boxes": [
            {
                "cls_id": 22,
                "label": "text",
                "score": 0.6943038702011108,
                "coordinate": [
                    65.958740234375,
                    74.09640502929688,
                    592.3479614257812,
                    104.8555908203125
                ]
            },
            {
                "cls_id": 22,
                "label": "text",
                "score": 0.970851480960846,
                "coordinate": [
                    64.3336181640625,
                    128.71775817871094,
                    1122.2445068359375,
                    192.2692413330078
                ]
            },
            {
                "cls_id": 22,
                "label": "text",
                "score": 0.941623330116272,
                "coordinate": [
                    66.7540283203125,
                    200.82308959960938,
                    786.8502197265625,
                    229.17587280273438
                ]
            },
            {
                "cls_id": 22,
                "label": "text",
                "score": 0.9630217552185059,
                "coordinate": [
                    65.1712646484375,
                    236.6416015625,
                    1122.19482421875,
                    301.2691650390625
                ]
            },
            {
                "cls_id": 17,
                "label": "paragraph_title",
                "score": 0.9082680940628052,
                "coordinate": [
                    113.00542449951172,
                    347.46453857421875,
                    191.11419677734375,
                    376.60113525390625
                ]
            },
            {
                "cls_id": 22,
                "label": "text",
                "score": 0.9586100578308105,
                "coordinate": [
                    77.1885986328125,
                    398.798095703125,
                    1061.4803466796875,
                    463.2843017578125
                ]
            },
            {
                "cls_id": 22,
                "label": "text",
                "score": 0.8686890006065369,
                "coordinate": [
                    102.87384033203125,
                    471.285400390625,
                    1010.2022094726562,
                    536.7752685546875
                ]
            },
            {
                "cls_id": 22,
                "label": "text",
                "score": 0.896490216255188,
                "coordinate": [
                    76.37667846679688,
                    578.646240234375,
                    1049.1102294921875,
                    608.956298828125
                ]
            },
            {
                "cls_id": 22,
                "label": "text",
                "score": 0.7564412355422974,
                "coordinate": [
                    96.91159057617188,
                    615.1121826171875,
                    900.11328125,
                    645.4512939453125
                ]
            },
            {
                "cls_id": 17,
                "label": "paragraph_title",
                "score": 0.8753977417945862,
                "coordinate": [
                    113.75985717773438,
                    704.5284423828125,
                    252.25198364257812,
                    732.1907958984375
                ]
            },
            {
                "cls_id": 22,
                "label": "text",
                "score": 0.9565345644950867,
                "coordinate": [
                    81.64144897460938,
                    746.6463012695312,
                    1086.5235595703125,
                    811.2168579101562
                ]
            },
            {
                "cls_id": 22,
                "label": "text",
                "score": 0.9281247854232788,
                "coordinate": [
                    88.787109375,
                    842.455078125,
                    280.0420837402344,
                    869.7791748046875
                ]
            },
            {
                "cls_id": 22,
                "label": "text",
                "score": 0.8854034543037415,
                "coordinate": [
                    125.25453186035156,
                    887.2188720703125,
                    402.62548828125,
                    918.2452392578125
                ]
            },
            {
                "cls_id": 22,
                "label": "text",
                "score": 0.9239590764045715,
                "coordinate": [
                    87.95152282714844,
                    958.4765625,
                    298.52850341796875,
                    985.655517578125
                ]
            },
            {
                "cls_id": 22,
                "label": "text",
                "score": 0.6081741452217102,
                "coordinate": [
                    126.47284698486328,
                    1048.5780029296875,
                    359.63671875,
                    1078.4857177734375
                ]
            },
            {
                "cls_id": 22,
                "label": "text",
                "score": 0.443416953086853,
                "coordinate": [
                    615.994384765625,
                    1032.361572265625,
                    911.18017578125,
                    1062.860107421875
                ]
            },
            {
                "cls_id": 22,
                "label": "text",
                "score": 0.6430659890174866,
                "coordinate": [
                    616.508544921875,
                    1031.776611328125,
                    1035.4779052734375,
                    1098.024658203125
                ]
            },
            {
                "cls_id": 22,
                "label": "text",
                "score": 0.4245328903198242,
                "coordinate": [
                    660.5587158203125,
                    1068.9619140625,
                    1034.5567626953125,
                    1097.42333984375
                ]
            },
            {
                "cls_id": 22,
                "label": "text",
                "score": 0.9398723840713501,
                "coordinate": [
                    94.34576416015625,
                    1135.190673828125,
                    930.5353393554688,
                    1200.626708984375
                ]
            },
            {
                "cls_id": 22,
                "label": "text",
                "score": 0.9374479651451111,
                "coordinate": [
                    94.13449096679688,
                    1231.0623779296875,
                    869.3614501953125,
                    1260.8572998046875
                ]
            }
        ]
    }
}