{
    "input_path": "pdf/중급_금융투자상품.pdf",
    "page_index": 3,
    "page_count": 19,
    "width": 1191,
    "height": 1684,
    "model_settings": {
        "use_doc_preprocessor": false,
        "use_layout_detection": true,
        "use_chart_recognition": false,
        "format_block_content": false,
        "merge_layout_blocks": true,
        "markdown_ignore_labels": [
            "number",
            "footnote",
            "header",
            "header_image",
            "footer",
            "footer_image",
            "aside_text"
        ]
    },
    "parsing_res_list": [
        {
            "block_label": "doc_title",
            "block_content": "제3장 투자권유 희망 투자자에 대한 판매",
            "block_bbox": [
                353,
                75,
                836,
                111
            ],
            "block_id": 0,
            "block_order": 1,
            "group_id": 0
        },
        {
            "block_label": "paragraph_title",
            "block_content": "제1절 투자자 정보",
            "block_bbox": [
                497,
                155,
                692,
                187
            ],
            "block_id": 1,
            "block_order": 2,
            "group_id": 1
        },
        {
            "block_label": "text",
            "block_content": "제7조(투자자정보 파악 및 투자자성향 분석 등)",
            "block_bbox": [
                66,
                227,
                464,
                254
            ],
            "block_id": 2,
            "block_order": 3,
            "group_id": 2
        },
        {
            "block_label": "text",
            "block_content": "① 임직원은 투자권유를 희망하는 투자자에 대하여 투자권유 전에 면담·질문 등을 통하여 투자자의 투자정보를 [별지 1]의 '투자자정보 확인서'에 따라 파악하고, 투자자정보 분석 결과표에 투자자로부터 서명 등의 방법으로 확인을 받아 이를 유지·관리하여야 한다.",
            "block_bbox": [
                65,
                263,
                1123,
                362
            ],
            "block_id": 3,
            "block_order": 4,
            "group_id": 3
        },
        {
            "block_label": "text",
            "block_content": "② 임직원은 제1항에 따라 확인한 투자자정보의 내용 및 투자자성향 결과를 고객에게 지체없이 제공하여야 한다.",
            "block_bbox": [
                65,
                370,
                1004,
                399
            ],
            "block_id": 4,
            "block_order": 5,
            "group_id": 4
        },
        {
            "block_label": "text",
            "block_content": "이 경우 은행은 위임의 범위에 투자자정보 작성 권한이 포함되어 있는지를 확인하여야 한다.",
            "block_bbox": [
                65,
                478,
                831,
                507
            ],
            "block_id": 5,
            "block_order": 6,
            "group_id": 5
        },
        {
            "block_label": "text",
            "block_content": "④ 임직원은 [별지 5]에 의해 투자권유 희망 여부 및 투자자정보 제공 여부를 확인하여야 한다. 이 때 일반금융소비자가 투자 자정보를 제공하지 아니하는 경우 은행은 적합성 원칙 준수 의무를 부담하지 않으며, 투자권유를 희망하지 않거나 설명을 요청하지 않는 경우 은행이 설명의무를 부담하지 않음을 고지하고 상담을 종료한다.",
            "block_bbox": [
                64,
                513,
                1123,
                616
            ],
            "block_id": 6,
            "block_order": 7,
            "group_id": 6
        },
        {
            "block_label": "paragraph_title",
            "block_content": "제8조(투자자정보의 유효기간)",
            "block_bbox": [
                66,
                656,
                322,
                683
            ],
            "block_id": 7,
            "block_order": 8,
            "group_id": 7
        },
        {
            "block_label": "text",
            "block_content": "① 임직원은 투자자로부터 별도의 변경 요청이 없으면 투자자 정보를 파악한 날로부터 24개월(투자자정보 유효기간) 동안 투자자정보가 변경되지 않은 것으로 간주할 수 있다.",
            "block_bbox": [
                65,
                690,
                1123,
                754
            ],
            "block_id": 8,
            "block_order": 9,
            "group_id": 8
        },
        {
            "block_label": "text",
            "block_content": "② 임직원은 투자권유 시마다 투자자에게 투자자정보 파악에 대해 안내하고 서명 등의 방법으로 확인을 받아야 한다.",
            "block_bbox": [
                65,
                762,
                1035,
                791
            ],
            "block_id": 9,
            "block_order": 10,
            "group_id": 9
        },
        {
            "block_label": "text",
            "block_content": "③ 임직원은 은행이 이미 투자자정보를 알고 있는 투자자에 대하여 투자권유를 하고자 하는 경우 투자자정보 유효기간 경과 여부를 확인하고, 유효기간이 지난 경우에는 투자자정보를 다시 파악하여야 한다.",
            "block_bbox": [
                65,
                798,
                1123,
                863
            ],
            "block_id": 10,
            "block_order": 11,
            "group_id": 10
        },
        {
            "block_label": "paragraph_title",
            "block_content": "제2절 투자권유",
            "block_bbox": [
                512,
                903,
                675,
                934
            ],
            "block_id": 11,
            "block_order": 12,
            "group_id": 11
        },
        {
            "block_label": "text",
            "block_content": "제9조(투자권유 절차)",
            "block_bbox": [
                66,
                974,
                251,
                1001
            ],
            "block_id": 12,
            "block_order": 13,
            "group_id": 12
        },
        {
            "block_label": "text",
            "block_content": "① 임직원은 투자자정보 분석결과에 따라 투자자성향과 그 의미에 대해 설명하고 그에 적합하게 투자권유를 하여야 한다.",
            "block_bbox": [
                65,
                1010,
                1071,
                1038
            ],
            "block_id": 13,
            "block_order": 14,
            "group_id": 13
        },
        {
            "block_label": "text",
            "block_content": "② 임직원은 은행이 이미 투자자정보를 알고 있는 투자자에 대하여는 기존 투자자성향과 그 의미에 대해 설명하고 투자권유를 하는 것이 바람직하다.",
            "block_bbox": [
                65,
                1045,
                1121,
                1109
            ],
            "block_id": 14,
            "block_order": 15,
            "group_id": 14
        },
        {
            "block_label": "text",
            "block_content": "③ 임직원은 투자자가 본인에게 적합하지 않은 것으로 판단되는 위험도의 포트폴리오에 투자할 것을 요청하는 경우 투자자문서비스를 제공할 수 없음을 알리고 자문계약 권유를 종료한다.",
            "block_bbox": [
                65,
                1118,
                1121,
                1182
            ],
            "block_id": 15,
            "block_order": 16,
            "group_id": 15
        },
        {
            "block_label": "text",
            "block_content": "④ 임직원은 투자자문 수행 시 투자자 보호를 위해 녹취가 필요한 경우에 한해 사전에 녹취 사실을 고지하고 상품에 대한 주요 내용에 대해 투자자에게 설명하였음을 녹취하여야 한다. 녹취 의무 대상 고객이 녹취를 희망하지 않는 경우에는 불건전영업행위에 해당되므로 투자자문을 중단한다. 투자자가 요청하는 경우 녹취한 파일을 제공하여야 한다.",
            "block_bbox": [
                65,
                1189,
                1122,
                1290
            ],
            "block_id": 16,
            "block_order": 17,
            "group_id": 16
        },
        {
            "block_label": "text",
            "block_content": "⑤ 임직원은 투자자문 수행 시 다음의 어느 하나에 해당하는 경우 투자자가 상품구조, 투자위험을 충분히 숙지하여 투자결정을 할 수 있도록 2영업일 이상의 숙려기간을 부여하고, 숙려기간이 경과한 후 투자자에게 계약의 승낙의사를 확인하여야 한다.",
            "block_bbox": [
                65,
                1297,
                1120,
                1362
            ],
            "block_id": 17,
            "block_order": 18,
            "group_id": 17
        },
        {
            "block_label": "text",
            "block_content": "1. 만65세 이상 고령투자자를 대상으로 “숙려제도 대상상품”을 판매하는 경우",
            "block_bbox": [
                100,
                1369,
                753,
                1397
            ],
            "block_id": 18,
            "block_order": 19,
            "group_id": 18
        },
        {
            "block_label": "text",
            "block_content": "2. 일반투자자를 대상으로 고난도 금융투자상품을 판매하는 경우",
            "block_bbox": [
                100,
                1405,
                641,
                1433
            ],
            "block_id": 19,
            "block_order": 20,
            "group_id": 19
        },
        {
            "block_label": "text",
            "block_content": "제10조(고령투자자에 대한 금융투자상품 판매시 보호 기준)",
            "block_bbox": [
                66,
                1471,
                563,
                1498
            ],
            "block_id": 20,
            "block_order": 21,
            "group_id": 20
        },
        {
            "block_label": "text",
            "block_content": "임직원은 고령투자자에게 금융투자상품 투자자문계약 체결에 따라 금융투자상품을 판매하는 경우 [별지 2]의 적합성판단 기준과 [별지 6]의 강화된 고령투자자 보호 기준을 준수하여야 한다. 고령투자자 관련 사항 발생 시 [별지 7]「고령투자자 상담확인서」를 징구하며, 상담 후 해당 내용을 녹취 등으로 기록하여야 한다.",
            "block_bbox": [
                64,
                1507,
                1123,
                1609
            ],
            "block_id": 21,
            "block_order": 22,
            "group_id": 21
        }
    ],
    "layout_det_res": {
        "input_path": null,
        "page_index": null,
        "boxes": [
            {
                "cls_id": 6,
                "label": "doc_title",
                "score": 0.9549025893211365,
                "coordinate": [
                    353.3414001464844,
                    75.66241455078125,
                    836.2596435546875,
                    111.87692260742188
                ]
            },
            {
                "cls_id": 17,
                "label": "paragraph_title",
                "score": 0.7600672245025635,
                "coordinate": [
                    497.00982666015625,
                    155.9945068359375,
                    692.3451538085938,
                    187.00234985351562
                ]
            },
            {
                "cls_id": 22,
                "label": "text",
                "score": 0.885780394077301,
                "coordinate": [
                    66.13735961914062,
                    227.57965087890625,
                    464.3278503417969,
                    254.9476318359375
                ]
            },
            {
                "cls_id": 22,
                "label": "text",
                "score": 0.9768039584159851,
                "coordinate": [
                    65.78631591796875,
                    263.16064453125,
                    1123.866943359375,
                    362.32861328125
                ]
            },
            {
                "cls_id": 22,
                "label": "text",
                "score": 0.9476146697998047,
                "coordinate": [
                    65.78558349609375,
                    370.728515625,
                    1004.4827270507812,
                    399.4827880859375
                ]
            },
            {
                "cls_id": 22,
                "label": "text",
                "score": 0.4476313591003418,
                "coordinate": [
                    65.93417358398438,
                    478.722900390625,
                    831.570068359375,
                    507.2294921875
                ]
            },
            {
                "cls_id": 22,
                "label": "text",
                "score": 0.9653403759002686,
                "coordinate": [
                    64.82232666015625,
                    513.78515625,
                    1123.272216796875,
                    616.4091796875
                ]
            },
            {
                "cls_id": 17,
                "label": "paragraph_title",
                "score": 0.6039540767669678,
                "coordinate": [
                    66.60578155517578,
                    656.345458984375,
                    322.11322021484375,
                    683.352783203125
                ]
            },
            {
                "cls_id": 22,
                "label": "text",
                "score": 0.9650008082389832,
                "coordinate": [
                    65.16253662109375,
                    690.8413696289062,
                    1123.12353515625,
                    754.7655639648438
                ]
            },
            {
                "cls_id": 22,
                "label": "text",
                "score": 0.94526207447052,
                "coordinate": [
                    65.84326171875,
                    762.8135986328125,
                    1035.87158203125,
                    791.2864990234375
                ]
            },
            {
                "cls_id": 22,
                "label": "text",
                "score": 0.9555347561836243,
                "coordinate": [
                    65.03515625,
                    798.8350219726562,
                    1123.4449462890625,
                    863.9292602539062
                ]
            },
            {
                "cls_id": 17,
                "label": "paragraph_title",
                "score": 0.94182950258255,
                "coordinate": [
                    512.7869873046875,
                    903.647705078125,
                    675.5150146484375,
                    934.110107421875
                ]
            },
            {
                "cls_id": 22,
                "label": "text",
                "score": 0.5483923554420471,
                "coordinate": [
                    66.21207427978516,
                    974.3427734375,
                    251.73092651367188,
                    1001.617919921875
                ]
            },
            {
                "cls_id": 22,
                "label": "text",
                "score": 0.9385879039764404,
                "coordinate": [
                    65.56088256835938,
                    1010.1612548828125,
                    1071.5767822265625,
                    1038.1182861328125
                ]
            },
            {
                "cls_id": 22,
                "label": "text",
                "score": 0.9722391963005066,
                "coordinate": [
                    65.1011962890625,
                    1045.982666015625,
                    1121.7734375,
                    1109.572021484375
                ]
            },
            {
                "cls_id": 22,
                "label": "text",
                "score": 0.9748054146766663,
                "coordinate": [
                    65.361083984375,
                    1118.1318359375,
                    1121.952880859375,
                    1182.7685546875
                ]
            },
            {
                "cls_id": 22,
                "label": "text",
                "score": 0.9400304555892944,
                "coordinate": [
                    65.63677978515625,
                    1189.8653564453125,
                    1122.19873046875,
                    1290.9713134765625
                ]
            },
            {
                "cls_id": 22,
                "label": "text",
                "score": 0.42013320326805115,
                "coordinate": [
                    65.88784790039062,
                    1261.31787109375,
                    845.27490234375,
                    1290.3994140625
                ]
            },
            {
                "cls_id": 22,
                "label": "text",
                "score": 0.9475232362747192,
                "coordinate": [
                    65.64031982421875,
                    1297.831787109375,
                    1120.66748046875,
                    1362.436767578125
                ]
            },
            {
                "cls_id": 22,
                "label": "text",
                "score": 0.9473103284835815,
                "coordinate": [
                    100.239501953125,
                    1369.1689453125,
                    753.2425537109375,
                    1397.0517578125
                ]
            },
            {
                "cls_id": 22,
                "label": "text",
                "score": 0.9464226961135864,
                "coordinate": [
                    100.4912109375,
                    1405.041748046875,
                    641.073486328125,
                    1433.032958984375
                ]
            },
            {
                "cls_id": 22,
                "label": "text",
                "score": 0.7627691030502319,
                "coordinate": [
                    66.204833984375,
                    1471.628662109375,
                    563.0167846679688,
                    1498.132080078125
                ]
            },
            {
                "cls_id": 22,
                "label": "text",
                "score": 0.9566051959991455,
                "coordinate": [
                    64.7978515625,
                    1507.3426513671875,
                    1123.3450927734375,
                    1609.0787353515625
                ]
            }
        ]
    }
}